CHANGELOG.rst
COPYRIGHT.rst
LICENSE
MANIFEST.in
README
README.rst
setup.cfg
setup.py
doc/ExtendedSelenium2Library.html
src/ExtendedSelenium2Library/__init__.py
src/ExtendedSelenium2Library/version.py
src/ExtendedSelenium2Library/decorators/__init__.py
src/ExtendedSelenium2Library/decorators/docstring.py
src/ExtendedSelenium2Library/keywords/__init__.py
src/ExtendedSelenium2Library/keywords/extendedelement.py
src/ExtendedSelenium2Library/keywords/extendedjavascript.py
src/ExtendedSelenium2Library/keywords/extendedwaiting.py
src/ExtendedSelenium2Library/locators/__init__.py
src/ExtendedSelenium2Library/locators/extendedelementfinder.py
src/robotframework_extendedselenium2library.egg-info/PKG-INFO
src/robotframework_extendedselenium2library.egg-info/SOURCES.txt
src/robotframework_extendedselenium2library.egg-info/dependency_links.txt
src/robotframework_extendedselenium2library.egg-info/requires.txt
src/robotframework_extendedselenium2library.egg-info/top_level.txt