Metadata-Version: 1.1
Name: robotframework-extendedselenium2library
Version: 0.8.1
Summary: Extended Selenium2 web testing library for Robot Framework with AngularJS support
Home-page: https://github.com/rickypc/robotframework-extendedselenium2library
Author: Richard Huang
Author-email: rickypc@users.noreply.github.com
License: AGPL 3
Keywords: robot framework extended testing automation selenium selenium2 webdriver web protractor angular angularjs angular.js javascript karma webdev softwaretesting
Platform: any
Classifier: Development Status :: 4 - Beta
Classifier: Framework :: Robot Framework
Classifier: Intended Audience :: Developers
Classifier: License :: OSI Approved :: GNU Affero General Public License v3
Classifier: Programming Language :: Python :: 2.7
Classifier: Topic :: Software Development :: Testing
